odoo/addons/l10n_br_stock_account_report/README.rst
odoo/addons/l10n_br_stock_account_report/__init__.py
odoo/addons/l10n_br_stock_account_report/__manifest__.py
odoo/addons/l10n_br_stock_account_report/i18n/l10n_br_stock_account_report.pot
odoo/addons/l10n_br_stock_account_report/i18n/pt_BR.po
odoo/addons/l10n_br_stock_account_report/readme/CONFIGURE.rst
odoo/addons/l10n_br_stock_account_report/readme/CONTRIBUTORS.rst
odoo/addons/l10n_br_stock_account_report/readme/CREDITS.rst
odoo/addons/l10n_br_stock_account_report/readme/DESCRIPTION.rst
odoo/addons/l10n_br_stock_account_report/readme/HISTORY.rst
odoo/addons/l10n_br_stock_account_report/readme/INSTALL.rst
odoo/addons/l10n_br_stock_account_report/readme/USAGE.rst
odoo/addons/l10n_br_stock_account_report/report/l10n_br_p7_model_inventory_report.xml
odoo/addons/l10n_br_stock_account_report/report/l10n_br_p7_model_inventory_report_view.xml
odoo/addons/l10n_br_stock_account_report/static/description/icon.png
odoo/addons/l10n_br_stock_account_report/static/description/index.html
odoo/addons/l10n_br_stock_account_report/tests/__init__.py
odoo/addons/l10n_br_stock_account_report/tests/test_l10n_br_p7_model_inventory_report.py
odoo/addons/l10n_br_stock_account_report/wizards/__init__.py
odoo/addons/l10n_br_stock_account_report/wizards/l10n_br_p7_model_inventory_report_wizard.py
odoo/addons/l10n_br_stock_account_report/wizards/l10n_br_p7_model_inventory_report_wizard_view.xml
odoo12_addon_l10n_br_stock_account_report-12.0.1.2.1.dist-info/METADATA
odoo12_addon_l10n_br_stock_account_report-12.0.1.2.1.dist-info/WHEEL
odoo12_addon_l10n_br_stock_account_report-12.0.1.2.1.dist-info/top_level.txt
odoo12_addon_l10n_br_stock_account_report-12.0.1.2.1.dist-info/RECORD
